csnn/__init__.py
csnn/activation.py
csnn/containers.py
csnn/dropout.py
csnn/functional.py
csnn/init.py
csnn/linear.py
csnn/module.py
csnn/norm.py
csnn/recurrent.py
csnn/convex/__init__.py
csnn/convex/ficnn.py
csnn/convex/psd.py
csnn/convex/pwq.py
csnn/feedforward/__init__.py
csnn/feedforward/mlp.py
csnn-1.0.6.post3.dist-info/licenses/LICENSE
csnn-1.0.6.post3.dist-info/METADATA
csnn-1.0.6.post3.dist-info/WHEEL
csnn-1.0.6.post3.dist-info/top_level.txt
csnn-1.0.6.post3.dist-info/RECORD
