Metadata-Version: 2.4
Name: csnn
Version: 1.0.6.post3
Summary: Neural Networks with CasADi
Author-email: Filippo Airaldi <filippoairaldi@gmail.com>
License-Expression: MIT
Project-URL: Homepage, https://github.com/FilippoAiraldi/casadi-neural-nets
Project-URL: Bug Tracker, https://github.com/FilippoAiraldi/casadi-neural-nets/issues
Keywords: casadi,nonlinear-optimization,neural-networks
Classifier: Programming Language :: Python
Classifier: Programming Language :: Python :: 3 :: Only
Classifier: Programming Language :: Python :: 3.9
Classifier: Programming Language :: Python :: 3.10
Classifier: Programming Language :: Python :: 3.11
Classifier: Programming Language :: Python :: 3.12
Classifier: Programming Language :: Python :: 3.13
Classifier: Operating System :: OS Independent
Classifier: Intended Audience :: Science/Research
Classifier: Topic :: Scientific/Engineering :: Mathematics
Classifier: Topic :: Scientific/Engineering :: Artificial Intelligence
Requires-Python: >=3.9
License-File: LICENSE
Requires-Dist: casadi>=3.6.3
Requires-Dist: numpy>=1.24.2
Requires-Dist: typing_extensions>=4.6.0
Dynamic: license-file
